deepdiff/__init__.py
deepdiff/contenthash.py
deepdiff/diff.py
deepdiff/helper.py
deepdiff/search.py
yb_deepdiff-0.1.0.dist-info/LICENSE
yb_deepdiff-0.1.0.dist-info/WHEEL
yb_deepdiff-0.1.0.dist-info/METADATA
yb_deepdiff-0.1.0.dist-info/RECORD
