Metadata-Version: 2.1
Name: yb-deepdiff
Version: 0.1.0
Summary: 
Author: Yegor Shevchenko
Author-email: egorhs19@gmail.com
Requires-Python: >=2.7,<3.0
Classifier: Programming Language :: Python :: 2
Classifier: Programming Language :: Python :: 2.7
Requires-Dist: pyhamcrest (==1.8.5)
